{
  "title":"Opportunità da cogliere al volo",
  "subtitle": "Non perdere le ultime occasioni di finanziamento, verifica i bandi in scadenza.",
  "cards": [
    {
        "title": "Bando europeo in scadenza",
        "time": "13/02/2025",
        "tags_card": ["Apertura candidature - 30/01/2024","Chiusura candidature - 30/01/2025"],
        "image": "/assets/images/partners/image_ibm.png",
        "tags_image": ["Aperto"],
        "title_card": "project x",
        "text_card": "Lorem ipsum dolor sit amet consectetur adipisicing elit. Dicta sequi reprehenderit tempora quidem delectus esse temporibus quas blanditiis sit accusantium, fuga dolores, perspiciatis minus ullam laboriosam. Commodi asperiores quae a.",
        "text_announcement": "Partecipa al bando",
        "url_announcement": "https://google.com",
        "text_details": "Vai ai dettagli",
        "url_details": "https://eurospoort.it"
    }
  ]
}